{
    "os": "Windows-10-10.0.17763-SP0",
    "python": "3.9.7",
    "heartbeatAt": "2022-02-22T00:39:35.866900",
    "startedAt": "2022-02-22T00:39:33.868157",
    "docker": null,
    "gpu": "Quadro P4000",
    "gpu_count": 1,
    "cpu_count": 40,
    "cuda": null,
    "args": [
        "-f",
        "C:\\Users\\aar245\\AppData\\Roaming\\jupyter\\runtime\\kernel-ce8fce23-b2e6-49f6-947c-54394a29a3ed.json"
    ],
    "state": "running",
    "program": "Desktop/privacy_preserving_nn/src_3/main.ipynb",
    "root": "C:/Users/aar245/Desktop/privacy_preserving_nn",
    "git": {
        "remote": null,
        "commit": null
    },
    "email": null,
    "host": "en-ma-eerl",
    "username": "aar245",
    "executable": "C:\\Users\\aar245\\Anaconda3\\envs\\privacy_ml_env\\python.exe"
}
